CHANGES.txt
LICENSE.txt
MANIFEST.in
README.txt
setup.py
js/__init__.py
js.yui.egg-info/PKG-INFO
js.yui.egg-info/SOURCES.txt
js.yui.egg-info/dependency_links.txt
js.yui.egg-info/entry_points.txt
js.yui.egg-info/namespace_packages.txt
js.yui.egg-info/not-zip-safe
js.yui.egg-info/requires.txt
js.yui.egg-info/top_level.txt
js/yui/__init__.py
js/yui/prepare.py
js/yui/test_yui.txt
js/yui/resources/animation/animation-debug.js
js/yui/resources/animation/animation-min.js
js/yui/resources/animation/animation.js
js/yui/resources/assets/skins/sam/ajax-loader.gif
js/yui/resources/assets/skins/sam/asc.gif
js/yui/resources/assets/skins/sam/autocomplete.css
js/yui/resources/assets/skins/sam/back-h.png
js/yui/resources/assets/skins/sam/back-v.png
js/yui/resources/assets/skins/sam/bar-h.png
js/yui/resources/assets/skins/sam/bar-v.png
js/yui/resources/assets/skins/sam/bg-h.gif
js/yui/resources/assets/skins/sam/bg-v.gif
js/yui/resources/assets/skins/sam/blankimage.png
js/yui/resources/assets/skins/sam/button.css
js/yui/resources/assets/skins/sam/calendar.css
js/yui/resources/assets/skins/sam/carousel.css
js/yui/resources/assets/skins/sam/check0.gif
js/yui/resources/assets/skins/sam/check1.gif
js/yui/resources/assets/skins/sam/check2.gif
js/yui/resources/assets/skins/sam/colorpicker.css
js/yui/resources/assets/skins/sam/container.css
js/yui/resources/assets/skins/sam/datatable.css
js/yui/resources/assets/skins/sam/desc.gif
js/yui/resources/assets/skins/sam/dt-arrow-dn.png
js/yui/resources/assets/skins/sam/dt-arrow-up.png
js/yui/resources/assets/skins/sam/editor-knob.gif
js/yui/resources/assets/skins/sam/editor-sprite-active.gif
js/yui/resources/assets/skins/sam/editor-sprite.gif
js/yui/resources/assets/skins/sam/editor.css
js/yui/resources/assets/skins/sam/header_background.png
js/yui/resources/assets/skins/sam/hue_bg.png
js/yui/resources/assets/skins/sam/imagecropper.css
js/yui/resources/assets/skins/sam/layout.css
js/yui/resources/assets/skins/sam/layout_sprite.png
js/yui/resources/assets/skins/sam/loading.gif
js/yui/resources/assets/skins/sam/logger.css
js/yui/resources/assets/skins/sam/menu-button-arrow-disabled.png
js/yui/resources/assets/skins/sam/menu-button-arrow.png
js/yui/resources/assets/skins/sam/menu.css
