Metadata-Version: 1.0
Name: js.yui
Version: 2.8.2-1
Summary: fanstatic YUI
Home-page: UNKNOWN
Author: Fanstatic Developers
Author-email: fanstatic@googlegroups.com
License: BSD
Platform: UNKNOWN
